tf/serving/__init__.py
tf/serving/__init__.pyi
tf/serving/b64.py
tf/serving/cli.py
tf/serving/multibatch.py
tf/serving/request.py
tf/serving/types.py
tf_serving-0.1.6.dist-info/METADATA
tf_serving-0.1.6.dist-info/WHEEL
tf_serving-0.1.6.dist-info/entry_points.txt
tf_serving-0.1.6.dist-info/top_level.txt
tf_serving-0.1.6.dist-info/RECORD
