Metadata-Version: 2.1
Name: tf-serving
Version: 0.1.6
Summary: Client for OCR predictions against TensorFlow Serving
Author-email: Marcel Claramunt <marcel@moveread.com>
Project-URL: repo, https://github.com/marciclabas/tensorflow-ocr.git
Requires-Python: >=3.10
Requires-Dist: aiohttp
Requires-Dist: pydantic
Requires-Dist: haskellian
Requires-Dist: lazy-loader
Provides-Extra: cli
Requires-Dist: typer ; extra == 'cli'
Requires-Dist: files-dataset ; extra == 'cli'
Requires-Dist: orjson ; extra == 'cli'
